plspm/__init__.py
plspm/bootstrap.py
plspm/config.py
plspm/estimator.py
plspm/inner_model.py
plspm/inner_summary.py
plspm/mode.py
plspm/outer_model.py
plspm/plspm.py
plspm/scale.py
plspm/scheme.py
plspm/unidimensionality.py
plspm/util.py
plspm/weights.py
plspm-0.5.7.dist-info/LICENSE
plspm-0.5.7.dist-info/METADATA
plspm-0.5.7.dist-info/WHEEL
plspm-0.5.7.dist-info/top_level.txt
plspm-0.5.7.dist-info/RECORD
