Metadata-Version: 2.1
Name: plspm
Version: 0.5.7
Summary: A library implementing the Partial Least Squares Path Model algorithm
Home-page: https://github.com/googlecloudplatform/plspm-python
Author: Jez Humble
Author-email: humble@google.com
Classifier: Programming Language :: Python :: 3
Classifier: License :: OSI Approved :: GNU General Public License v3 (GPLv3)
Classifier: Operating System :: OS Independent
License-File: LICENSE
Requires-Dist: pandas
Requires-Dist: numpy
Requires-Dist: scipy
Requires-Dist: statsmodels
Requires-Dist: scikit-learn
